django_urlauth_egguy-0.3.0.dist-info/METADATA
django_urlauth_egguy-0.3.0.dist-info/WHEEL
django_urlauth_egguy-0.3.0.dist-info/licenses/AUTHORS
django_urlauth_egguy-0.3.0.dist-info/licenses/LICENSE
urlauth/__init__.py
urlauth/admin.py
urlauth/management/__init__.py
urlauth/management/commands/__init__.py
urlauth/management/commands/urlauth_cleanup.py
urlauth/middleware.py
urlauth/migrations/0001_initial.py
urlauth/migrations/__init__.py
urlauth/models.py
urlauth/settings.py
urlauth/signals.py
urlauth/util.py
django_urlauth_egguy-0.3.0.dist-info/RECORD
