Metadata-Version: 2.1
Name: django-urlauth-egguy
Version: 0.3.0
Summary: Django application for user authentication with key in hypertext link
Keywords: django application authentication authorization
Author-Email: egguy <etienne.guilluy@gmail.com>, Grigoriy Petukhov <lorien@lorien.name>
License: BSD
Classifier: Development Status :: 4 - Beta
Classifier: Environment :: Web Environment
Classifier: Framework :: Django
Classifier: Intended Audience :: Developers
Classifier: License :: OSI Approved :: BSD License
Classifier: Operating System :: OS Independent
Classifier: Programming Language :: Python
Classifier: Topic :: Utilities
Project-URL: Homepage, https://github.com/egguy/django-urlauth/
Requires-Python: >=3.8
Requires-Dist: django>=1.11
